MANIFEST.in
setup.py
clizy/__init__.py
clizy/cli_structures.py
clizy/core.py
clizy/docstring_processors.py
clizy.egg-info/PKG-INFO
clizy.egg-info/SOURCES.txt
clizy.egg-info/dependency_links.txt
clizy.egg-info/top_level.txt
docs/README.md
tests/tests_cli/__init__.py
tests/tests_cli/clizy_multiple_funcs.py
tests/tests_cli/clizy_one_func.py
tests/tests_cli/test_cli.py