Metadata-Version: 2.1
Name: clizy
Version: 1.0.1
Summary: Command-line interface creation for lazy people using type hints.
Home-page: https://github.com/prokopst/clizy
Author: Stan Prokop
License: Apache 2 License
Platform: UNKNOWN
Classifier: Intended Audience :: Developers
Classifier: Topic :: Software Development :: Libraries
Classifier: License :: OSI Approved :: Apache Software License
Classifier: Programming Language :: Python :: 3.6
